emrt.necd.theme-2.0.4-py2.7-nspkg.pth
emrt/necd/theme/__init__.py
emrt/necd/theme/configure.zcml
emrt/necd/theme/profiles.zcml
emrt/necd/theme/rebuild_i18n.sh
emrt/necd/theme/setuphandlers.py
emrt/necd/theme/skins.zcml
emrt/necd/theme/tests.py
emrt/necd/theme/browser/__init__.py
emrt/necd/theme/browser/configure.zcml
emrt/necd/theme/browser/interfaces.py
emrt/necd/theme/browser/viewlets.py
emrt/necd/theme/browser/template-overrides/CONTENTS.txt
emrt/necd/theme/browser/template-overrides/Products.CMFPlone.skins.plone_login.insufficient_privileges.pt
emrt/necd/theme/browser/template-overrides/Products.CMFPlone.skins.plone_login.insufficient_privileges.pt.metadata
emrt/necd/theme/browser/template-overrides/Products.CMFPlone.skins.plone_login.login_form.cpt
emrt/necd/theme/browser/template-overrides/Products.CMFPlone.skins.plone_login.login_form.cpt.metadata
emrt/necd/theme/browser/template-overrides/Products.CMFPlone.skins.plone_login.require_login.py
emrt/necd/theme/browser/template-overrides/Products.CMFPlone.skins.plone_templates.global_statusmessage.pt
emrt/necd/theme/browser/template-overrides/plone.app.discussion.browser.comments.pt
emrt/necd/theme/browser/template-overrides/plone.app.layout.viewlets.document_byline.pt
emrt/necd/theme/browser/templates/CONTENTS.txt
emrt/necd/theme/browser/templates/footer.pt
emrt/necd/theme/browser/templates/logo.pt
emrt/necd/theme/browser/templates/personal_bar.pt
emrt/necd/theme/browser/templates/product_version.pt
emrt/necd/theme/locales/emrt.necd.theme-manual.pot
emrt/necd/theme/locales/emrt.necd.theme.pot
emrt/necd/theme/locales/plone.pot
emrt/necd/theme/locales/en/LC_MESSAGES/emrt.necd.theme.po
emrt/necd/theme/locales/en/LC_MESSAGES/plone.po
emrt/necd/theme/profiles/default/actions.xml
emrt/necd/theme/profiles/default/cssregistry.xml
emrt/necd/theme/profiles/default/emrt.necd.theme_various.txt
emrt/necd/theme/profiles/default/jsregistry.xml
emrt/necd/theme/profiles/default/metadata.xml
emrt.necd.theme-2.0.4.dist-info/METADATA
emrt.necd.theme-2.0.4.dist-info/WHEEL
emrt.necd.theme-2.0.4.dist-info/entry_points.txt
emrt.necd.theme-2.0.4.dist-info/namespace_packages.txt
emrt.necd.theme-2.0.4.dist-info/top_level.txt
emrt.necd.theme-2.0.4.dist-info/RECORD
