Metadata-Version: 2.1
Name: emrt.necd.theme
Version: 2.0.4
Summary: Installable theme: emrt.necd.theme
Home-page: https://github.com/eea/emrt.necd.theme/
Author: Mikel Santamaria
Author-email: msantamaria@bilbomatica.es
License: GPL
Platform: UNKNOWN
Classifier: Framework :: Plone
Classifier: Programming Language :: Python
Requires-Dist: setuptools
Requires-Dist: z3c.jbot
Requires-Dist: eea.icons
Requires-Dist: emrt.necd.content
Requires-Dist: Products.Collage
